businessLogic/__init__.py
businessLogic/noteManager.py
businessLogic/userManager.py
businessLogic/validationException.py
dataAcces/__init__.py
dataAcces/context.py
dataAcces/noteDA.py
dataAcces/userDA.py
entites/__init__.py
entites/note.py
entites/user.py
infrastructure/__init__.py
infrastructure/configHelper.py
infrastructure/singleton.py
sample_backend-1.0.0.dist-info/LICENSE.txt
sample_backend-1.0.0.dist-info/METADATA
sample_backend-1.0.0.dist-info/WHEEL
sample_backend-1.0.0.dist-info/top_level.txt
sample_backend-1.0.0.dist-info/RECORD
