Metadata-Version: 2.1
Name: sample-backend
Version: 1.0.0
Summary: Sample backend for todo-list application
Home-page: https://github.com/malonejv/py-sample-backend
Author: Javier López Malone
Author-email: malonejv@gmail.com
License: MIT
Project-URL: Bug Tracker, https://github.com/malonejv/py-sample-backend/issues
Keywords: todolist,todo
Platform: UNKNOWN
Requires-Python: >=3.9
License-File: LICENSE.txt
